kubernetes_log_analysis/__init__.py
kubernetes_log_analysis/analyzer.py
kubernetes_log_analysis/cli.py
kubernetes_log_analysis/config.py
kubernetes_log_analysis/file_finder.py
kubernetes_log_analysis-0.1.0.dist-info/METADATA
kubernetes_log_analysis-0.1.0.dist-info/WHEEL
kubernetes_log_analysis-0.1.0.dist-info/entry_points.txt
kubernetes_log_analysis-0.1.0.dist-info/top_level.txt
kubernetes_log_analysis-0.1.0.dist-info/RECORD
