Metadata-Version: 2.4
Name: kubernetes-log-analysis
Version: 0.1.0
Summary: A tool to analyze Kubernetes log bundles using LLMs.
Home-page: https://github.com/ap-mic-inc/kubernetes-log-analysis
Author: Simon Liu / APMIC
Author-email: simonliuyuwei@gmail.com
Classifier: Programming Language :: Python :: 3
Classifier: License :: OSI Approved :: MIT License
Classifier: Operating System :: OS Independent
Classifier: Topic :: System :: Logging
Classifier: Topic :: Software Development :: Libraries :: Python Modules
Requires-Python: >=3.8
Requires-Dist: litellm>=1.34.0
Requires-Dist: click>=8.0
Requires-Dist: python-dotenv>=1.0.0
Dynamic: author
Dynamic: author-email
Dynamic: classifier
Dynamic: description
Dynamic: description-content-type
Dynamic: home-page
Dynamic: requires-dist
Dynamic: requires-python
Dynamic: summary
